assets/congeneric_reliability.r
audpsychometric/__init__.py
audpsychometric/core/__init__.py
audpsychometric/core/gold_standard.py
audpsychometric/core/reliability.py
audpsychometric/core/datasets/Hallgren-Table-03.csv
audpsychometric/core/datasets/Hallgren-Table-05.csv
audpsychometric/core/datasets/HolzingerSwineford1939.csv
audpsychometric/core/datasets/Shrout_Fleiss_1979.csv
audpsychometric/core/datasets/__init__.py
audpsychometric/core/datasets/datasets.csv
audpsychometric/core/datasets/statology.csv
audpsychometric/core/datasets/wine.csv
docs/bibliography.rst
docs/changelog.rst
docs/conf.py
docs/contributing.rst
docs/genindex.rst
docs/index.rst
docs/installation.rst
docs/refs.bib
docs/requirements.txt
docs/api-src/audpsychometric.rst
tests/conftest.py
tests/requirements.txt
tests/test_dataset.py
tests/test_gold_standard.py
tests/test_reliability.py
audpsychometric-0.1.1.dist-info/LICENSE
audpsychometric-0.1.1.dist-info/METADATA
audpsychometric-0.1.1.dist-info/WHEEL
audpsychometric-0.1.1.dist-info/top_level.txt
audpsychometric-0.1.1.dist-info/RECORD
