Metadata-Version: 2.1
Name: audpsychometric
Version: 0.1.1
Summary: Analyze and summarize human annotations
Author: Sandrine Lefort
Author-email: Hagen Wierstorf <hwierstorf@audeering.com>, Christian Geng <cgeng@audeering.com>
License: MIT License
Project-URL: repository, https://github.com/audeering/audpsychometric/
Project-URL: documentation, https://audeering.github.io/audpsychometric/
Keywords: audio,data,dataset,annotation,mlops,machine learning
Classifier: Development Status :: 5 - Production/Stable
Classifier: Intended Audience :: Science/Research
Classifier: Intended Audience :: Developers
Classifier: License :: OSI Approved :: MIT License
Classifier: Operating System :: OS Independent
Classifier: Programming Language :: Python
Classifier: Programming Language :: Python :: 3
Classifier: Programming Language :: Python :: 3.9
Classifier: Programming Language :: Python :: 3.10
Classifier: Programming Language :: Python :: 3.11
Classifier: Programming Language :: Python :: 3.12
Classifier: Topic :: Scientific/Engineering
License-File: LICENSE
Requires-Dist: audeer >=1.10.0
Requires-Dist: audmetric
Requires-Dist: pingouin
Requires-Dist: numpy <2.1
Requires-Dist: pandas
Requires-Dist: scikit-learn
Requires-Dist: statsmodels
